mice/__init__.py
mice/deltas.py
mice/mice.py
mice/plot_mice.py
mice-0.1.31.dist-info/LICENSE
mice-0.1.31.dist-info/METADATA
mice-0.1.31.dist-info/WHEEL
mice-0.1.31.dist-info/top_level.txt
mice-0.1.31.dist-info/RECORD
