Metadata-Version: 2.1
Name: mice
Version: 0.1.31
Summary: Multi-iteration Stochastic Estimator
Home-page: https://bitbucket.org/agcarlon/mice
Author: Andre Gustavo Carlon
Author-email: agcarlon@gmail.com
License: GPLv3
Project-URL: Documentation, https://mice.readthedocs.io/
Project-URL: Source, https://bitbucket.org/agcarlon/mice
Project-URL: Manuscript, https://arxiv.org/abs/2011.01718
Keywords: stochastic optimization,hierarchical methods,Monte Carlo
Classifier: Development Status :: 4 - Beta
Classifier: Intended Audience :: Science/Research
Classifier: Intended Audience :: Education
Classifier: Intended Audience :: Information Technology
Classifier: Topic :: Scientific/Engineering
Classifier: Topic :: Education
Classifier: Topic :: Utilities
Classifier: License :: OSI Approved :: GNU General Public License v3 (GPLv3)
Classifier: Programming Language :: Python :: 3
Classifier: Programming Language :: Python :: 3.6
Classifier: Programming Language :: Python :: 3.7
Classifier: Programming Language :: Python :: 3.8
Classifier: Programming Language :: Python :: 3.9
Classifier: Programming Language :: Python :: 3 :: Only
License-File: LICENSE
Requires-Dist: numpy >=1.19
Requires-Dist: scipy >=1.8.1
Requires-Dist: pandas >=1.1
Requires-Dist: matplotlib >=3.2.0
